abch_tree_sitter_solidity-1.3.1.data/data/src/parser.c
abch_tree_sitter_solidity-1.3.1.data/data/src/parser.h
tree_sitter_solidity/__init__.py
tree_sitter_solidity/core.py
tree_sitter_solidity/solidity.so
abch_tree_sitter_solidity-1.3.1.dist-info/METADATA
abch_tree_sitter_solidity-1.3.1.dist-info/WHEEL
abch_tree_sitter_solidity-1.3.1.dist-info/top_level.txt
abch_tree_sitter_solidity-1.3.1.dist-info/RECORD
abch_tree_sitter_solidity-1.3.1.dist-info/licenses/LICENSE
