Metadata-Version: 2.4
Name: abch_tree_sitter_solidity
Version: 1.3.1
Summary: Solidity grammar for the Tree-sitter parsing library
Home-page: https://github.com/Ackee-Blockchain/tree-sitter-solidity
Author: Ackee Blockchain
License: MIT
Project-URL: Source, https://github.com/Ackee-Blockchain/tree-sitter-solidity
Platform: any
Requires-Python: >=3.7
License-File: LICENSE
Requires-Dist: abch-tree-sitter>=1.0.1
Dynamic: author
Dynamic: description
Dynamic: description-content-type
Dynamic: home-page
Dynamic: license
Dynamic: license-file
Dynamic: platform
Dynamic: project-url
Dynamic: requires-dist
Dynamic: requires-python
Dynamic: summary
